{
  "version": 1,
  "serial": 4,
  "modules": [
    {
      "name": "zsh-theme-ultimate",
      "metadata": {
        "type": "github",
        "address": "https://github.com/b4b4r07/ultimate"
      },
      "home": "/Users/b4b4r07/.antidote/github.com/b4b4r07/ultimate",
      "result": "not started yet",
      "error": "repository already exists",
      "resources": []
    },
    {
      "name": "enhancd",
      "metadata": {
        "type": "github",
        "address": "https://github.com/b4b4r07/enhancd"
      },
      "home": "/Users/b4b4r07/.antidote/github.com/b4b4r07/enhancd",
      "result": "not started yet",
      "error": "repository already exists",
      "resources": []
    },
    {
      "name": "zsh-vimode",
      "metadata": {
        "type": "github",
        "address": "https://github.com/b4b4r07/zsh-vimode-visual"
      },
      "home": "/Users/b4b4r07/.antidote/github.com/b4b4r07/zsh-vimode-visual",
      "result": "not started yet",
      "error": "repository already exists",
      "resources": []
    },
    {
      "name": "zsh-history",
      "metadata": {
        "type": "github",
        "address": "https://github.com/b4b4r07/history"
      },
      "home": "/Users/b4b4r07/.antidote/github.com/b4b4r07/history",
      "result": "not started yet",
      "error": "repository already exists",
      "resources": []
    },
    {
      "name": "hoge",
      "metadata": {
        "type": "github",
        "address": "https://github.com/ahmetb/kubectx"
      },
      "home": "/Users/b4b4r07/.antidote/github.com/ahmetb/kubectx",
      "result": "not started yet",
      "error": "repository already exists",
      "resources": []
    },
    {
      "name": "cd-improvement",
      "metadata": {
        "type": "github",
        "address": "https://github.com/changyuheng/zsh-interactive-cd"
      },
      "home": "/Users/b4b4r07/.antidote/github.com/changyuheng/zsh-interactive-cd",
      "result": "not started yet",
      "error": "repository already exists",
      "resources": []
    },
    {
      "name": "minimal",
      "metadata": {
        "type": "github",
        "address": "https://github.com/subnixr/minimal"
      },
      "home": "/Users/b4b4r07/.antidote/github.com/subnixr/minimal",
      "result": "not started yet",
      "error": "repository already exists",
      "resources": []
    },
    {
      "name": "git-open",
      "metadata": {
        "type": "github",
        "address": "https://github.com/paulirish/git-open"
      },
      "home": "/Users/b4b4r07/.antidote/github.com/paulirish/git-open",
      "result": "not started yet",
      "error": "repository already exists",
      "resources": []
    },
    {
      "name": "prok",
      "metadata": {
        "type": "github",
        "address": "https://github.com/mutantcornholio/prok"
      },
      "home": "/Users/b4b4r07/.antidote/github.com/mutantcornholio/prok",
      "result": "not started yet",
      "error": "repository already exists",
      "resources": []
    },
    {
      "name": "zsh-history-search",
      "metadata": {
        "type": "github",
        "address": "https://github.com/zdharma/history-search-multi-word"
      },
      "home": "/Users/b4b4r07/.antidote/github.com/zdharma/history-search-multi-word",
      "result": "not started yet",
      "error": "repository already exists",
      "resources": []
    },
    {
      "name": "zsh-highlight",
      "metadata": {
        "type": "github",
        "address": "https://github.com/zdharma/fast-syntax-highlighting"
      },
      "home": "/Users/b4b4r07/.antidote/github.com/zdharma/fast-syntax-highlighting",
      "result": "not started yet",
      "error": "repository already exists",
      "resources": []
    },
    {
      "name": "fzy",
      "metadata": {
        "type": "github",
        "address": "https://github.com/jhawthorn/fzy"
      },
      "home": "/Users/b4b4r07/.antidote/github.com/jhawthorn/fzy",
      "result": "not started yet",
      "error": "repository already exists",
      "resources": []
    },
    {
      "name": "envchain",
      "metadata": {
        "type": "github",
        "address": "https://github.com/sorah/envchain"
      },
      "home": "/Users/b4b4r07/.antidote/github.com/sorah/envchain",
      "result": "not started yet",
      "error": "repository already exists",
      "resources": []
    },
    {
      "name": "zsh-highlight-disable",
      "metadata": {
        "type": "github",
        "address": "https://github.com/zsh-users/zsh-syntax-highlighting"
      },
      "home": "/Users/b4b4r07/.antidote/github.com/zsh-users/zsh-syntax-highlighting",
      "result": "not started yet",
      "error": "repository already exists",
      "resources": []
    },
    {
      "name": "agkozak-zsh-prompt",
      "metadata": {
        "type": "github",
        "address": "https://github.com/agkozak/agkozak-zsh-prompt"
      },
      "home": "/Users/b4b4r07/.antidote/github.com/agkozak/agkozak-zsh-prompt",
      "result": "not started yet",
      "error": "repository already exists",
      "resources": []
    },
    {
      "name": "exa",
      "metadata": {
        "type": "github",
        "address": "https://github.com/ogham/exa"
      },
      "home": "/Users/b4b4r07/.antidote/github.com/ogham/exa",
      "result": "not started yet",
      "error": "reading file in zip archive: file already exists: /Users/b4b4r07/.antidote/github.com/ogham/exa/exa-macos-x86_64",
      "resources": []
    },
    {
      "name": "fzf",
      "metadata": {
        "type": "github",
        "address": "https://github.com/junegunn/fzf-bin"
      },
      "home": "/Users/b4b4r07/.antidote/github.com/junegunn/fzf-bin",
      "result": "not started yet",
      "error": "reading file in tar archive: file already exists: /Users/b4b4r07/.antidote/github.com/junegunn/fzf-bin/fzf",
      "resources": []
    },
    {
      "name": "jq",
      "metadata": {
        "type": "github",
        "address": "https://github.com/stedolan/jq"
      },
      "home": "/Users/b4b4r07/.antidote/github.com/stedolan/jq",
      "result": "not started yet",
      "error": "",
      "resources": []
    },
    {
      "name": "fillin",
      "metadata": {
        "type": "github",
        "address": "https://github.com/itchyny/fillin"
      },
      "home": "/Users/b4b4r07/.antidote/github.com/itchyny/fillin",
      "result": "not started yet",
      "error": "reading file in zip archive: file already exists: /Users/b4b4r07/.antidote/github.com/itchyny/fillin/fillin_darwin_amd64/LICENSE",
      "resources": []
    },
    {
      "name": "peco",
      "metadata": {
        "type": "github",
        "address": "https://github.com/peco/peco"
      },
      "home": "/Users/b4b4r07/.antidote/github.com/peco/peco",
      "result": "not started yet",
      "error": "reading file in zip archive: file already exists: /Users/b4b4r07/.antidote/github.com/peco/peco/peco_darwin_386/Changes",
      "resources": []
    },
    {
      "name": "gkill",
      "metadata": {
        "type": "github",
        "address": "https://github.com/heppu/gkill"
      },
      "home": "/Users/b4b4r07/.antidote/github.com/heppu/gkill",
      "result": "not started yet",
      "error": "",
      "resources": []
    },
    {
      "name": "pet",
      "metadata": {
        "type": "github",
        "address": "https://github.com/knqyf263/pet"
      },
      "home": "/Users/b4b4r07/.antidote/github.com/knqyf263/pet",
      "result": "not started yet",
      "error": "reading file in tar archive: file already exists: /Users/b4b4r07/.antidote/github.com/knqyf263/pet/LICENSE",
      "resources": []
    },
    {
      "name": "gron",
      "metadata": {
        "type": "github",
        "address": "https://github.com/tomnomnom/gron"
      },
      "home": "/Users/b4b4r07/.antidote/github.com/tomnomnom/gron",
      "result": "not started yet",
      "error": "reading file in tar archive: file already exists: /Users/b4b4r07/.antidote/github.com/tomnomnom/gron/gron",
      "resources": []
    },
    {
      "name": "hub",
      "metadata": {
        "type": "github",
        "address": "https://github.com/github/hub"
      },
      "home": "/Users/b4b4r07/.antidote/github.com/github/hub",
      "result": "not started yet",
      "error": "reading file in tar archive: file already exists: /Users/b4b4r07/.antidote/github.com/github/hub/hub-darwin-amd64-2.12.3/README.md",
      "resources": []
    },
    {
      "name": "docker-compose",
      "metadata": {
        "type": "github",
        "address": "https://github.com/docker/compose"
      },
      "home": "/Users/b4b4r07/.antidote/github.com/docker/compose",
      "result": "not started yet",
      "error": "",
      "resources": []
    },
    {
      "name": "neovim",
      "metadata": {
        "type": "github",
        "address": "https://github.com/neovim/neovim"
      },
      "home": "/Users/b4b4r07/.antidote/github.com/neovim/neovim",
      "result": "not started yet",
      "error": "reading file in tar archive: file already exists: /Users/b4b4r07/.antidote/github.com/neovim/neovim/nvim-osx64/Users/travis/build/neovim/bot-ci/build/neovim/.deps/usr/share/man/man1/gperf.1",
      "resources": []
    },
    {
      "name": "kustomize",
      "metadata": {
        "type": "github",
        "address": "https://github.com/kubernetes-sigs/kustomize"
      },
      "home": "/Users/b4b4r07/.antidote/github.com/kubernetes-sigs/kustomize",
      "result": "not started yet",
      "error": "",
      "resources": []
    },
    {
      "name": "gobump",
      "metadata": {
        "type": "github",
        "address": "https://github.com/motemen/gobump"
      },
      "home": "/Users/b4b4r07/.antidote/github.com/motemen/gobump",
      "result": "not started yet",
      "error": "",
      "resources": [
        {
          "path": "/Users/b4b4r07/.antidote/github.com/motemen/gobump/gobump",
          "to": "/Users/b4b4r07/bin/gobump"
        }
      ]
    },
    {
      "name": "ghq",
      "metadata": {
        "type": "github",
        "address": "https://github.com/motemen/ghq"
      },
      "home": "/Users/b4b4r07/.antidote/github.com/motemen/ghq",
      "result": "not started yet",
      "error": "",
      "resources": []
    }
  ]
}
